pveautomate/__init__.py
pveautomate/automate.py
pveautomate-0.3.2.dist-info/LICENSE
pveautomate-0.3.2.dist-info/METADATA
pveautomate-0.3.2.dist-info/WHEEL
pveautomate-0.3.2.dist-info/top_level.txt
pveautomate-0.3.2.dist-info/RECORD
