Metadata-Version: 2.2
Name: pveautomate
Version: 0.3.2
Summary: A package to automate Proxmox VE tasks
Home-page: https://github.com/alchemicode/pveautomate
Author: Matt Compton
Author-email: matt@alchemicode.com
Classifier: Programming Language :: Python :: 3
Classifier: License :: OSI Approved :: MIT License
Classifier: Operating System :: OS Independent
Requires-Python: >=3.6
License-File: LICENSE
Requires-Dist: requests
Dynamic: author
Dynamic: author-email
Dynamic: classifier
Dynamic: description
Dynamic: description-content-type
Dynamic: home-page
Dynamic: requires-dist
Dynamic: requires-python
Dynamic: summary
